IIAOptimize/Linearsys.py
IIAOptimize/Onedim.py
IIAOptimize/__init__.py
IIAOptimize/multidim.py
IIAOptimize-0.0.1.dist-info/LICENCE.txt
IIAOptimize-0.0.1.dist-info/METADATA
IIAOptimize-0.0.1.dist-info/WHEEL
IIAOptimize-0.0.1.dist-info/top_level.txt
IIAOptimize-0.0.1.dist-info/RECORD
